crustyfuzz-0.1.3.dist-info/METADATA
crustyfuzz-0.1.3.dist-info/WHEEL
crustyfuzz-0.1.3.dist-info/licenses/LICENSE
crustyfuzz/distance/damerau_levenshtein.pyi
crustyfuzz/distance/hamming.pyi
crustyfuzz/distance/indel.pyi
crustyfuzz/distance/jaro.pyi
crustyfuzz/distance/jaro_winkler.pyi
crustyfuzz/distance/lcs_seq.pyi
crustyfuzz/distance/levenshtein.pyi
crustyfuzz/distance/metrics.py
crustyfuzz/distance/osa.pyi
crustyfuzz/distance/postfix.pyi
crustyfuzz/distance/prefix.pyi
crustyfuzz/distance/_initialize.py
crustyfuzz/distance/_initialize.pyi
crustyfuzz/distance/__init__.py
crustyfuzz/distance/__init__.pyi
crustyfuzz/fuzz.pyi
crustyfuzz/process.pyi
crustyfuzz/py.typed
crustyfuzz/utils.py
crustyfuzz/__init__.py
crustyfuzz/crustyfuzz.pyd
crustyfuzz-0.1.3.dist-info/RECORD
