Metadata-Version: 2.4
Name: crustyfuzz
Version: 0.1.3
Classifier: Development Status :: 4 - Beta
Classifier: Intended Audience :: Developers
Classifier: License :: OSI Approved :: MIT License
Classifier: Operating System :: OS Independent
Classifier: Programming Language :: Rust
Classifier: Programming Language :: Python
Classifier: Programming Language :: Python :: 3.8
Classifier: Programming Language :: Python :: 3.9
Classifier: Programming Language :: Python :: 3.10
Classifier: Programming Language :: Python :: 3.11
Classifier: Programming Language :: Python :: 3.12
Classifier: Programming Language :: Python :: 3 :: Only
Classifier: Programming Language :: Python :: Implementation :: CPython
Classifier: Programming Language :: Python :: Implementation :: PyPy
Classifier: Topic :: Software Development :: Libraries
Classifier: Topic :: Software Development :: Libraries :: Python Modules
Classifier: Typing :: Typed
Requires-Dist: numpy >=1.24.4 ; extra == 'numpy'
Requires-Dist: pandas >=2.0.3 ; extra == 'numpy'
Requires-Dist: pandas-stubs >=2.0.2.230605 ; extra == 'numpy'
Requires-Dist: matplotlib >=3.7.5 ; extra == 'plot'
Requires-Dist: pyqt6 >=6.7.1 ; extra == 'plot'
Provides-Extra: numpy
Provides-Extra: plot
License-File: LICENSE
Requires-Python: >=3.8
